[
  {
    "id": 1,
    "name": "The Lagos Elite Kitchen",
    "cuisine": "Gourmet Jollof & Grills",
    "rating": 4.9,
    "time": "25-45 min",
    "delivery": "Free Delivery",
    "image": "https://images.unsplash.com/photo-1590846406792-0adc7f938f1d?auto=format&fit=crop&w=800&q=80"
  },
  {
    "id": 2,
    "name": "Calabar Heritage Dining",
    "cuisine": "Native Soups & Seafood",
    "rating": 4.7,
    "time": "30-50 min",
    "delivery": "₦2,500 Delivery",
    "image": "https://images.unsplash.com/photo-1517248135467-4c7edcad34c4?auto=format&fit=crop&w=800&q=80"
  },
  {
    "id": 3,
    "name": "Abuja Royal Grill",
    "cuisine": "Suya, Asun & Game Meat",
    "rating": 4.8,
    "time": "15-30 min",
    "delivery": "Free Delivery",
    "image": "https://images.unsplash.com/photo-1552566626-52f8b828add9?auto=format&fit=crop&w=800&q=80"
  },
  {
    "id": 4,
    "name": "The Enugu Hearth",
    "cuisine": "Traditional Swallows",
    "rating": 4.6,
    "time": "20-40 min",
    "delivery": "₦1,500 Delivery",
    "image": "https://images.unsplash.com/photo-1555396273-367ea4eb4db5?auto=format&fit=crop&w=800&q=80"
  },
  {
    "id": 5,
    "name": "Zuma Artisan Drinks",
    "cuisine": "Palm Wine & Cocktails",
    "rating": 4.9,
    "time": "10-20 min",
    "delivery": "Free Delivery",
    "image": "https://images.unsplash.com/photo-1514362545857-3bc16c4c7d1b?auto=format&fit=crop&w=800&q=80"
  },
  {
    "id": 6,
    "name": "Ibadan Sweet Bakes",
    "cuisine": "Small Chops & Pastries",
    "rating": 4.7,
    "time": "20-30 min",
    "delivery": "₦3,500 Delivery",
    "image": "https://images.unsplash.com/photo-1555507036-ab1f4038808a?auto=format&fit=crop&w=800&q=80"
  }
]
